lipidhandler/__init__.py
lipidhandler/dictionaries.py
lipidhandler/helper.py
lipidhandler/lipid.py
lipidhandler/lipidclass.py
lipidhandler/lipidlist.py
lipidhandler/residue.py
lipidhandler/residuelist.py
lipidhandler/residuemodification.py
lipidhandler/xref.py
lipidhandler/xreflist.py
lipidhandler/zstate.py
lipidhandler/zstatelist.py
lipidhandler/externalapis/__init__.py
lipidhandler/externalapis/apimodel.py
lipidhandler/externalapis/swisslipids.py
lipidhandler-0.0.6.dist-info/LICENSE
lipidhandler-0.0.6.dist-info/METADATA
lipidhandler-0.0.6.dist-info/WHEEL
lipidhandler-0.0.6.dist-info/top_level.txt
lipidhandler-0.0.6.dist-info/RECORD
