Metadata-Version: 2.1
Name: lipidhandler
Version: 0.0.6
Summary: Handle lipid names in Python.
Home-page: https://github.com/kaiserpreusse/lipidhandler
Author: Martin Preusse
Author-email: martin.preusse@gmail.com
License: MIT
Keywords: LIPIDS,LIPIDOMICS
Platform: UNKNOWN
Classifier: Programming Language :: Python
Classifier: Development Status :: 3 - Alpha
Classifier: Intended Audience :: Developers
Classifier: License :: OSI Approved :: Apache Software License
Requires-Dist: requests
